<?xml version="1.0" encoding="UTF-8"?>
<schemalist>
  <schema id="org.gnome.shell.extensions.icon-manager" path="/org/gnome/shell/extensions/icon-manager/">
    <key type="as" name="top-bar">
      <default>[]</default>
      <summary>Top Bar icons</summary>
      <description>List of icons that will be removed from top panel. 
      Icons:  a11y (accessibility icon), display, keyboard, volume, bluetooth, network, battery
      </description>
    </key>
    <key type="as" name="tray-bar">
      <default>[]</default>
      <summary>Bottom Bar icons</summary>
      <description>List of icons that will be moved from tray to top panel, e.g. tomboy</description>
    </key>
  </schema>
</schemalist>
